{"allContent":{"docusaurus-plugin-content-docs":{"default":{"loadedVersions":[{"versionName":"current","label":"Next","banner":null,"badge":false,"noIndex":false,"className":"docs-version-current","path":"/quantstack.github.io/docs","tagsPath":"/quantstack.github.io/docs/tags","editUrl":"https://github.com/facebook/docusaurus/tree/main/packages/create-docusaurus/templates/shared/docs","editUrlLocalized":"https://github.com/facebook/docusaurus/tree/main/packages/create-docusaurus/templates/shared/i18n/en/docusaurus-plugin-content-docs/current","isLast":true,"routePriority":-1,"sidebarFilePath":"/home/fhaudin/dev/new.quantstack.github.io/sidebars.ts","contentPath":"/home/fhaudin/dev/new.quantstack.github.io/docs","contentPathLocalized":"/home/fhaudin/dev/new.quantstack.github.io/i18n/en/docusaurus-plugin-content-docs/current","docs":[{"id":"intro","title":"Tutorial Intro","description":"Let's discover Docusaurus in less than 5 minutes.","source":"@site/docs/intro.md","sourceDirName":".","slug":"/intro","permalink":"/quantstack.github.io/docs/intro","draft":false,"unlisted":false,"editUrl":"https://github.com/facebook/docusaurus/tree/main/packages/create-docusaurus/templates/shared/docs/intro.md","tags":[],"version":"current","sidebarPosition":1,"frontMatter":{"sidebar_position":1},"sidebar":"tutorialSidebar"}],"drafts":[],"sidebars":{"tutorialSidebar":[{"type":"doc","id":"intro"}]}}]}},"docusaurus-plugin-content-blog":{"default":{"blogSidebarTitle":"Recent posts","blogPosts":[],"blogListPaginated":[],"blogTags":{},"blogTagsListPath":"/quantstack.github.io/blog/tags"}},"docusaurus-plugin-content-pages":{"default":[{"type":"jsx","permalink":"/quantstack.github.io/about","source":"@site/src/pages/about.tsx"},{"type":"jsx","permalink":"/quantstack.github.io/blog","source":"@site/src/pages/blog.tsx"},{"type":"jsx","permalink":"/quantstack.github.io/careers","source":"@site/src/pages/careers.tsx"},{"type":"jsx","permalink":"/quantstack.github.io/contact","source":"@site/src/pages/contact.tsx"},{"type":"jsx","permalink":"/quantstack.github.io/home","source":"@site/src/pages/home.tsx"},{"type":"jsx","permalink":"/quantstack.github.io/","source":"@site/src/pages/index.tsx"},{"type":"jsx","permalink":"/quantstack.github.io/projects","source":"@site/src/pages/projects.tsx"},{"type":"jsx","permalink":"/quantstack.github.io/services","source":"@site/src/pages/services.tsx"},{"type":"jsx","permalink":"/quantstack.github.io/blogs/Fanny","source":"@site/src/pages/blogs/Fanny.tsx"},{"type":"jsx","permalink":"/quantstack.github.io/projects/condaforge","source":"@site/src/pages/projects/condaforge.tsx"},{"type":"jsx","permalink":"/quantstack.github.io/projects/jupyter","source":"@site/src/pages/projects/jupyter.tsx"},{"type":"jsx","permalink":"/quantstack.github.io/projects/robotics","source":"@site/src/pages/projects/robotics.tsx"},{"type":"jsx","permalink":"/quantstack.github.io/projects/xtensorxsimd","source":"@site/src/pages/projects/xtensorxsimd.tsx"}]},"docusaurus-plugin-debug":{},"docusaurus-theme-classic":{},"docusaurus-bootstrap-plugin":{},"docusaurus-mdx-fallback-plugin":{}}}